{
  "albuns": [
    {
      "id": 1,
      "titulo": "Cuidador de idoso",
      "descricao": "Especialista em cuidados estou na aréa a mais de 5 anos",
      "latitude": "-20.387504744554168",
      "longitude": "-43.5008735069115",
      "data": "09-05-2023",
      "urldacapa": "imgs/usuario.png"
    },
    {
      "id": 2,
      "titulo": "Fernanda",
      "descricao": "Amo ajudar os animais",
      "latitude": "-22.86910033724501",
      "longitude": "-46.032784252853766",
      "data": "09-05-2023",
      "urldacapa": "imgs/usuario.png"
    },
    {
      "id": 3,
      "titulo": "Geisy",
      "descricao": "Apaixonada pela culinária",
      "latitude": "21.110565368394518",
      "longitude": "-44.166785650366066",
      "data": "09-05-2023",
      "urldacapa": ""
    }
  ],
  "servicos": [
    {
      "id": 1,
      "nome": "Cuidador de idoso",
      "categoria": "Outros",
      "descricao": "Sou um profissional comprometido em fornecer um ambiente seguro e carinhoso para idosos",
      "localizacao": "Nome da rua, num, Bairro, Cidade",
      "foto": "img/usuario.png",
      "disponibilidade": "12:00",
      "preco": 50,
      "data": "2023-12-31",
      "contato": true
    },
    {
      "nome": "Jardinagem e Paisagismo",
      "categoria": "Jardinagem",
      "descricao": "especialista em jardinagem e paisagismo",
      "localizacao": "Nome da rua, num, Bairro, Cidade",
      "foto": "img/usuario.png",
      "disponibilidade": "12:00",
      "preco": 50,
      "data": "2023-12-31",
      "contato": true,
      "id": 2
    }
   
    
  ]
}